ykfan_utils/__init__.py
ykfan_utils/camera/Camera.py
ykfan_utils/camera/__init__.py
ykfan_utils/dataset/CrowdHuman.py
ykfan_utils/dataset/DataSetRead.py
ykfan_utils/dataset/FDDB.py
ykfan_utils/dataset/WiderFace.py
ykfan_utils/dataset/__init__.py
ykfan_utils/dataset/dataset_util.py
ykfan_utils/dataset/res_show.py
ykfan_utils/demo/__init__.py
ykfan_utils/demo/data.txt
ykfan_utils/demo/example.py
ykfan_utils/directory/__init__.py
ykfan_utils/directory/dir_utils.py
ykfan_utils/image/__init__.py
ykfan_utils/image/nms.py
ykfan_utils/image/preprocess.py
ykfan_utils/test/__init__.py
ykfan_utils/test/example_test.py
ykfan_utils/tflite/__init__.py
ykfan_utils/tflite/tflite_convert.py
ykfan_utils/tflite/tflite_use.py
ykfan_utils/time/__init__.py
ykfan_utils/time/time_utils.py
ykfan_utils-0.0.17.dist-info/LICENSE
ykfan_utils-0.0.17.dist-info/METADATA
ykfan_utils-0.0.17.dist-info/WHEEL
ykfan_utils-0.0.17.dist-info/top_level.txt
ykfan_utils-0.0.17.dist-info/RECORD
