Metadata-Version: 2.1
Name: ykfan-utils
Version: 0.0.17
Summary: ykfan utils for deep learning
Home-page: https://github.com/fanyongkang87/ykfan_utils.git
Author: ykfan
Author-email: fanyongkang87@qq.com
License: UNKNOWN
Platform: UNKNOWN
Classifier: Programming Language :: Python :: 2.7
Classifier: Programming Language :: Python :: 3.7
Classifier: License :: OSI Approved :: MIT License
Classifier: Operating System :: OS Independent
